[{"ID":0,"Text":"____________________searching for '@elonmusk' now____________________","CreatedAt":"","Entities":null},{"ID":1476740887543791617,"Text":"@TheBabylonBee 🤣","CreatedAt":"Fri Dec 31 02:23:58 +0000 2021","Entities":{"hashtags":[],"media":null,"urls":[],"user_mentions":[{"indices":[0,14],"id":4914384040,"id_str":"4914384040","name":"The Babylon Bee","screen_name":"TheBabylonBee"}]}},{"ID":1476662222617251846,"Text":"@roshanpateI 🤣 $7","CreatedAt":"Thu Dec 30 21:11:23 +0000 2021","Entities":{"hashtags":[],"media":null,"urls":[],"user_mentions":[{"indices":[0,12],"id":816354391880040450,"id_str":"816354391880040450","name":"Roshan Patel","screen_name":"roshanpateI"}]}},{"ID":1476656306610216960,"Text":"@tesla_raj Many UI improvements coming","CreatedAt":"Thu Dec 30 20:47:53 +0000 2021","Entities":{"hashtags":[],"media":null,"urls":[],"user_mentions":[{"indices":[0,10],"id":1061504849420836865,"id_str":"1061504849420836865","name":"Tesla Raj","screen_name":"tesla_raj"}]}},{"ID":1476651519986614281,"Text":"@CSmithson80 @heydave7 @BLKMDL3 @mims This chart is a big deal","CreatedAt":"Thu Dec 30 20:28:51 +0000 2021","Entities":{"hashtags":[],"media":null,"urls":[],"user_mentions":[{"indices":[0,12],"id":2904581459,"id_str":"2904581459","name":"Chris Smithson","screen_name":"CSmithson80"},{"indices":[13,22],"id":29893444,"id_str":"29893444","name":"Dave Lee","screen_name":"heydave7"},{"indices":[23,31],"id":988975103785365504,"id_str":"988975103785365504","name":"Zack","screen_name":"BLKMDL3"},{"indices":[32,37],"id":1769191,"id_str":"1769191","name":"Christopher Mims 🤌","screen_name":"mims"}]}},{"ID":1476619907076923398,"Text":"@BLKMDL3 @mims Predicting macroeconomics is challenging, to say the least. My gut feel is maybe around spring or su… https://t.co/nBqZB9gsAy","CreatedAt":"Thu Dec 30 18:23:14 +0000 2021","Entities":{"hashtags":[],"media":null,"urls":[{"indices":[117,140],"display_url":"twitter.com/i/web/status/1…","expanded_url":"https://twitter.com/i/web/status/1476619907076923398","url":"https://t.co/nBqZB9gsAy"}],"user_mentions":[{"indices":[0,8],"id":988975103785365504,"id_str":"988975103785365504","name":"Zack","screen_name":"BLKMDL3"},{"indices":[9,14],"id":1769191,"id_str":"1769191","name":"Christopher Mims 🤌","screen_name":"mims"}]}},{"ID":1476618021024190474,"Text":"@mims If history is any guide, not many will make it past the next recession","CreatedAt":"Thu Dec 30 18:15:45 +0000 2021","Entities":{"hashtags":[],"media":null,"urls":[],"user_mentions":[{"indices":[0,5],"id":1769191,"id_str":"1769191","name":"Christopher Mims 🤌","screen_name":"mims"}]}},{"ID":1476607954719752199,"Text":"@waitbutwhy 💯🙏","CreatedAt":"Thu Dec 30 17:35:45 +0000 2021","Entities":{"hashtags":[],"media":null,"urls":[],"user_mentions":[{"indices":[0,11],"id":1282121312,"id_str":"1282121312","name":"Tim Urban","screen_name":"waitbutwhy"}]}},{"ID":1476473842059161602,"Text":"@T_Ball5 Probably not wrong","CreatedAt":"Thu Dec 30 08:42:50 +0000 2021","Entities":{"hashtags":[],"media":null,"urls":[],"user_mentions":[{"indices":[0,8],"id":1419528326,"id_str":"1419528326","name":"TBALL5","screen_name":"T_Ball5"}]}},{"ID":1476450321786359810,"Text":"@heydave7 🤔","CreatedAt":"Thu Dec 30 07:09:22 +0000 2021","Entities":{"hashtags":[],"media":null,"urls":[],"user_mentions":[{"indices":[0,9],"id":29893444,"id_str":"29893444","name":"Dave Lee","screen_name":"heydave7"}]}},{"ID":1476439722046238725,"Text":"https://t.co/OCUqr6xd9d","CreatedAt":"Thu Dec 30 06:27:15 +0000 2021","Entities":{"hashtags":[],"media":[{"indices":[0,23],"display_url":"pic.twitter.com/OCUqr6xd9d","expanded_url":"https://twitter.com/elonmusk/status/1476439722046238725/photo/1","url":"https://t.co/OCUqr6xd9d","id":1476439719277907968,"id_str":"1476439719277907968","media_url":"http://pbs.twimg.com/media/FH1eGifWUAAAxmM.jpg","media_url_https":"https://pbs.twimg.com/media/FH1eGifWUAAAxmM.jpg","source_status_id":0,"source_status_id_str":"","type":"photo","sizes":{"thumb":{"w":150,"h":150,"resize":"crop"},"large":{"w":1170,"h":1153,"resize":"fit"},"medium":{"w":1170,"h":1153,"resize":"fit"},"small":{"w":680,"h":670,"resize":"fit"}},"video_info":{"aspect_ratio":[0,0],"duration_millis":0,"variants":null}}],"urls":[],"user_mentions":[]}},{"ID":1476437555717541893,"Text":"https://t.co/mVhCpxVPZI","CreatedAt":"Thu Dec 30 06:18:38 +0000 2021","Entities":{"hashtags":[],"media":[{"indices":[0,23],"display_url":"pic.twitter.com/mVhCpxVPZI","expanded_url":"https://twitter.com/elonmusk/status/1476437555717541893/photo/1","url":"https://t.co/mVhCpxVPZI","id":1476437553683312644,"id_str":"1476437553683312644","media_url":"http://pbs.twimg.com/media/FH1cIfBXMAQsROP.jpg","media_url_https":"https://pbs.twimg.com/media/FH1cIfBXMAQsROP.jpg","source_status_id":0,"source_status_id_str":"","type":"photo","sizes":{"thumb":{"w":150,"h":150,"resize":"crop"},"large":{"w":406,"h":333,"resize":"fit"},"medium":{"w":406,"h":333,"resize":"fit"},"small":{"w":406,"h":333,"resize":"fit"}},"video_info":{"aspect_ratio":[0,0],"duration_millis":0,"variants":null}}],"urls":[],"user_mentions":[]}},{"ID":1476242084126511105,"Text":"@PPathole I do","CreatedAt":"Wed Dec 29 17:21:54 +0000 2021","Entities":{"hashtags":[],"media":null,"urls":[],"user_mentions":[{"indices":[0,9],"id":1291945442,"id_str":"1291945442","name":"Pranay Pathole","screen_name":"PPathole"}]}},{"ID":1476229496244166658,"Text":"@GailAlfarATX @SawyerMerritt Wow, working on this problem has soaked up a lot of my time \u0026amp; brain cycles over the pa… https://t.co/vPDW3GYGUp","CreatedAt":"Wed Dec 29 16:31:53 +0000 2021","Entities":{"hashtags":[],"media":null,"urls":[{"indices":[121,144],"display_url":"twitter.com/i/web/status/1…","expanded_url":"https://twitter.com/i/web/status/1476229496244166658","url":"https://t.co/vPDW3GYGUp"}],"user_mentions":[{"indices":[0,13],"id":1233929232432205827,"id_str":"1233929232432205827","name":"Gail Alfar (Austin)","screen_name":"GailAlfarATX"},{"indices":[14,28],"id":243013409,"id_str":"243013409","name":"Sawyer Merritt","screen_name":"SawyerMerritt"}]}},{"ID":1476227079033303042,"Text":"@SawyerMerritt Ashok was the first person recruited from my tweet saying that Tesla is starting an Autopilot team!","CreatedAt":"Wed Dec 29 16:22:17 +0000 2021","Entities":{"hashtags":[],"media":null,"urls":[],"user_mentions":[{"indices":[0,14],"id":243013409,"id_str":"243013409","name":"Sawyer Merritt","screen_name":"SawyerMerritt"}]}},{"ID":1476220099682082816,"Text":"@esprit_tesla @chazman @lexfridman Yes","CreatedAt":"Wed Dec 29 15:54:33 +0000 2021","Entities":{"hashtags":[],"media":null,"urls":[],"user_mentions":[{"indices":[0,13],"id":1190525944714452992,"id_str":"1190525944714452992","name":"Esprit Tesla","screen_name":"esprit_tesla"},{"indices":[14,22],"id":14084713,"id_str":"14084713","name":"Chuck Cook","screen_name":"chazman"},{"indices":[23,34],"id":427089628,"id_str":"427089628","name":"Lex Fridman","screen_name":"lexfridman"}]}},{"ID":1476110401347670017,"Text":"@risermaker @engineers_feed ~700nm to ~400nm","CreatedAt":"Wed Dec 29 08:38:39 +0000 2021","Entities":{"hashtags":[],"media":null,"urls":[],"user_mentions":[{"indices":[0,11],"id":1304442754546774017,"id_str":"1304442754546774017","name":"high vibration (Ðoge-1)","screen_name":"risermaker"},{"indices":[12,27],"id":3429950987,"id_str":"3429950987","name":"World of Engineering","screen_name":"engineers_feed"}]}},{"ID":1476109841949208577,"Text":"@SirineAti @engineers_feed FAA approval is the schedule driver. Their latest update says end of February.","CreatedAt":"Wed Dec 29 08:36:25 +0000 2021","Entities":{"hashtags":[],"media":null,"urls":[],"user_mentions":[{"indices":[0,10],"id":1285872552766734346,"id_str":"1285872552766734346","name":"💫Sirine💫","screen_name":"SirineAti"},{"indices":[11,26],"id":3429950987,"id_str":"3429950987","name":"World of Engineering","screen_name":"engineers_feed"}]}},{"ID":1475939200218370049,"Text":"Lex asks great questions https://t.co/TlyuEGoOVA","CreatedAt":"Tue Dec 28 21:18:21 +0000 2021","Entities":{"hashtags":[],"media":null,"urls":[{"indices":[25,48],"display_url":"twitter.com/lexfridman/sta…","expanded_url":"https://twitter.com/lexfridman/status/1475907489463943168","url":"https://t.co/TlyuEGoOVA"}],"user_mentions":[]}},{"ID":1475561126645710850,"Text":"@cleantechnica Most people still have no idea that sustainable energy generation is growing so fast","CreatedAt":"Mon Dec 27 20:16:01 +0000 2021","Entities":{"hashtags":[],"media":null,"urls":[],"user_mentions":[{"indices":[0,14],"id":17060015,"id_str":"17060015","name":"CleanTechnica","screen_name":"cleantechnica"}]}},{"ID":1475540629891522566,"Text":"@SpaceXMR 🤣","CreatedAt":"Mon Dec 27 18:54:35 +0000 2021","Entities":{"hashtags":[],"media":null,"urls":[],"user_mentions":[{"indices":[0,9],"id":1004697063974633472,"id_str":"1004697063974633472","name":"/r/SpaceX Masterrace","screen_name":"SpaceXMR"}]}},{"ID":1475431151321899012,"Text":"@engineers_feed The resolution of the universe is not smaller than Planck length\nhttps://t.co/hoyZR4d0pP","CreatedAt":"Mon Dec 27 11:39:33 +0000 2021","Entities":{"hashtags":[],"media":null,"urls":[{"indices":[81,104],"display_url":"en.m.wikipedia.org/wiki/Planck_le…","expanded_url":"https://en.m.wikipedia.org/wiki/Planck_length","url":"https://t.co/hoyZR4d0pP"}],"user_mentions":[{"indices":[0,15],"id":3429950987,"id_str":"3429950987","name":"World of Engineering","screen_name":"engineers_feed"}]}},{"ID":1475321407328432131,"Text":"@karpathy All of reality can be simulated with ones \u0026amp; zeroes","CreatedAt":"Mon Dec 27 04:23:28 +0000 2021","Entities":{"hashtags":[],"media":null,"urls":[],"user_mentions":[{"indices":[0,9],"id":33836629,"id_str":"33836629","name":"Andrej Karpathy","screen_name":"karpathy"}]}},{"ID":1475318524390293515,"Text":"@lexfridman Yeah, the smarter someone is, the harder it is to simulate/predict their behavior","CreatedAt":"Mon Dec 27 04:12:00 +0000 2021","Entities":{"hashtags":[],"media":null,"urls":[],"user_mentions":[{"indices":[0,11],"id":427089628,"id_str":"427089628","name":"Lex Fridman","screen_name":"lexfridman"}]}},{"ID":1475318038379569156,"Text":"@BillyM2k Now that the Webb telescope has been launched, they will have to spend more on rendering haha","CreatedAt":"Mon Dec 27 04:10:05 +0000 2021","Entities":{"hashtags":[],"media":null,"urls":[],"user_mentions":[{"indices":[0,9],"id":30699048,"id_str":"30699048","name":"Shibetoshi Nakamoto","screen_name":"BillyM2k"}]}},{"ID":1475317711165169665,"Text":"@BillyM2k It is simulations all the way down, until you get to one bit","CreatedAt":"Mon Dec 27 04:08:47 +0000 2021","Entities":{"hashtags":[],"media":null,"urls":[],"user_mentions":[{"indices":[0,9],"id":30699048,"id_str":"30699048","name":"Shibetoshi Nakamoto","screen_name":"BillyM2k"}]}},{"ID":1475314495396405256,"Text":"@PPathole People are able to break any laws made by humans, but none made by physics","CreatedAt":"Mon Dec 27 03:56:00 +0000 2021","Entities":{"hashtags":[],"media":null,"urls":[],"user_mentions":[{"indices":[0,9],"id":1291945442,"id_str":"1291945442","name":"Pranay Pathole","screen_name":"PPathole"}]}},{"ID":1475313375597019140,"Text":"Physics formulas are the rendering rules","CreatedAt":"Mon Dec 27 03:51:33 +0000 2021","Entities":{"hashtags":[],"media":null,"urls":[],"user_mentions":[]}},{"ID":1475312943420121088,"Text":"So much of AI is about compressing reality to a small vector space, like a video game in reverse","CreatedAt":"Mon Dec 27 03:49:50 +0000 2021","Entities":{"hashtags":[],"media":null,"urls":[],"user_mentions":[]}},{"ID":1475189931995709441,"Text":"@stats_feed @engineers_feed Useful mass to orbit is what matters","CreatedAt":"Sun Dec 26 19:41:02 +0000 2021","Entities":{"hashtags":[],"media":null,"urls":[],"user_mentions":[{"indices":[0,11],"id":1335132884278108161,"id_str":"1335132884278108161","name":"World of Statistics","screen_name":"stats_feed"},{"indices":[12,27],"id":3429950987,"id_str":"3429950987","name":"World of Engineering","screen_name":"engineers_feed"}]}},{"ID":1475184726621175808,"Text":"@nichegamer 🤣","CreatedAt":"Sun Dec 26 19:20:21 +0000 2021","Entities":{"hashtags":[],"media":null,"urls":[],"user_mentions":[{"indices":[0,11],"id":1558996520,"id_str":"1558996520","name":"Niche Gamer","screen_name":"nichegamer"}]}},{"ID":1475182936559435777,"Text":"@DimaZeniuk @klwtts @TeslaClubNorway @WholeMarsBlog @SawyerMerritt @1stMarsColonist @daelmor @Kristennetten… https://t.co/eFo3HD86vs","CreatedAt":"Sun Dec 26 19:13:14 +0000 2021","Entities":{"hashtags":[],"media":null,"urls":[{"indices":[109,132],"display_url":"twitter.com/i/web/status/1…","expanded_url":"https://twitter.com/i/web/status/1475182936559435777","url":"https://t.co/eFo3HD86vs"}],"user_mentions":[{"indices":[0,11],"id":1198495865301864448,"id_str":"1198495865301864448","name":"Dima Zeniuk","screen_name":"DimaZeniuk"},{"indices":[12,19],"id":912969880852299776,"id_str":"912969880852299776","name":"The Kilowatts 🚗⚡️","screen_name":"klwtts"},{"indices":[20,36],"id":2994611423,"id_str":"2994611423","name":"TeslaOwnersClubNorway","screen_name":"TeslaClubNorway"},{"indices":[37,51],"id":1263491240336769026,"id_str":"1263491240336769026","name":"Whole Mars","screen_name":"WholeMarsBlog"},{"indices":[52,66],"id":243013409,"id_str":"243013409","name":"Sawyer Merritt","screen_name":"SawyerMerritt"},{"indices":[67,83],"id":1320429075270307846,"id_str":"1320429075270307846","name":"Ash Martian ✨🌎🚀🔴✨","screen_name":"1stMarsColonist"},{"indices":[84,92],"id":97552785,"id_str":"97552785","name":"𝔇𝔞𝔫𝔞 (Fairy Dogmother 🧚‍♀️🐩🐾)","screen_name":"daelmor"},{"indices":[93,107],"id":985686123123949568,"id_str":"985686123123949568","name":"•K10•✨","screen_name":"Kristennetten"}]}},{"ID":1475081021423038468,"Text":"https://t.co/Scr3Ub3tgT","CreatedAt":"Sun Dec 26 12:28:15 +0000 2021","Entities":{"hashtags":[],"media":[{"indices":[0,23],"display_url":"pic.twitter.com/Scr3Ub3tgT","expanded_url":"https://twitter.com/elonmusk/status/1475081021423038468/photo/1","url":"https://t.co/Scr3Ub3tgT","id":1475081018524811267,"id_str":"1475081018524811267","media_url":"http://pbs.twimg.com/media/FHiKXvwXwAMwNtu.jpg","media_url_https":"https://pbs.twimg.com/media/FHiKXvwXwAMwNtu.jpg","source_status_id":0,"source_status_id_str":"","type":"photo","sizes":{"thumb":{"w":150,"h":150,"resize":"crop"},"large":{"w":919,"h":808,"resize":"fit"},"medium":{"w":919,"h":808,"resize":"fit"},"small":{"w":680,"h":598,"resize":"fit"}},"video_info":{"aspect_ratio":[0,0],"duration_millis":0,"variants":null}}],"urls":[],"user_mentions":[]}},{"ID":1475076745627938821,"Text":"@archillect Now $1.25","CreatedAt":"Sun Dec 26 12:11:16 +0000 2021","Entities":{"hashtags":[],"media":null,"urls":[],"user_mentions":[{"indices":[0,11],"id":2907774137,"id_str":"2907774137","name":"Archillect","screen_name":"archillect"}]}},{"ID":1474909274459578380,"Text":"@NASA @NASAWebb Congratulations, this is major!","CreatedAt":"Sun Dec 26 01:05:48 +0000 2021","Entities":{"hashtags":[],"media":null,"urls":[],"user_mentions":[{"indices":[0,5],"id":11348282,"id_str":"11348282","name":"NASA","screen_name":"NASA"},{"indices":[6,15],"id":29472803,"id_str":"29472803","name":"NASA Webb Telescope","screen_name":"NASAWebb"}]}},{"ID":1474908839979925508,"Text":"@WorldAndScience Me 💯","CreatedAt":"Sun Dec 26 01:04:04 +0000 2021","Entities":{"hashtags":[],"media":null,"urls":[],"user_mentions":[{"indices":[0,16],"id":511402689,"id_str":"511402689","name":"World and Science","screen_name":"WorldAndScience"}]}},{"ID":1474860884359094275,"Text":"Floki Santa https://t.co/y3CTq16bGi","CreatedAt":"Sat Dec 25 21:53:31 +0000 2021","Entities":{"hashtags":[],"media":[{"indices":[12,35],"display_url":"pic.twitter.com/y3CTq16bGi","expanded_url":"https://twitter.com/elonmusk/status/1474860884359094275/photo/1","url":"https://t.co/y3CTq16bGi","id":1474860878780682252,"id_str":"1474860878780682252","media_url":"http://pbs.twimg.com/media/FHfCJ7TX0AwDyHE.jpg","media_url_https":"https://pbs.twimg.com/media/FHfCJ7TX0AwDyHE.jpg","source_status_id":0,"source_status_id_str":"","type":"photo","sizes":{"thumb":{"w":150,"h":150,"resize":"crop"},"large":{"w":1425,"h":1806,"resize":"fit"},"medium":{"w":947,"h":1200,"resize":"fit"},"small":{"w":537,"h":680,"resize":"fit"}},"video_info":{"aspect_ratio":[0,0],"duration_millis":0,"variants":null}}],"urls":[],"user_mentions":[]}},{"ID":1474836752619741188,"Text":"Merry Christmas 🎄🎁 ⛄️ ⭐️ 😃","CreatedAt":"Sat Dec 25 20:17:37 +0000 2021","Entities":{"hashtags":[],"media":null,"urls":[],"user_mentions":[]}},{"ID":1474834326571397120,"Text":"@JonErlichman Or Tesla!","CreatedAt":"Sat Dec 25 20:07:59 +0000 2021","Entities":{"hashtags":[],"media":null,"urls":[],"user_mentions":[{"indices":[0,13],"id":164425558,"id_str":"164425558","name":"Jon Erlichman","screen_name":"JonErlichman"}]}},{"ID":1474493189688070148,"Text":"Interesting\nhttps://t.co/548FHpnnxU","CreatedAt":"Fri Dec 24 21:32:25 +0000 2021","Entities":{"hashtags":[],"media":null,"urls":[{"indices":[12,35],"display_url":"census.gov/newsroom/press…","expanded_url":"https://www.census.gov/newsroom/press-releases/2021/2021-population-estimates.html","url":"https://t.co/548FHpnnxU"}],"user_mentions":[]}},{"ID":1474491417816973321,"Text":"@nichegamer It’s good","CreatedAt":"Fri Dec 24 21:25:23 +0000 2021","Entities":{"hashtags":[],"media":null,"urls":[],"user_mentions":[{"indices":[0,11],"id":1558996520,"id_str":"1558996520","name":"Niche Gamer","screen_name":"nichegamer"}]}},{"ID":1474481634770567170,"Text":"@PPathole @Tesla That was a crazy tough year. Tesla financing closed at 6pm Christmas Eve – last hour of the last d… https://t.co/rwM2zi1XfJ","CreatedAt":"Fri Dec 24 20:46:30 +0000 2021","Entities":{"hashtags":[],"media":null,"urls":[{"indices":[117,140],"display_url":"twitter.com/i/web/status/1…","expanded_url":"https://twitter.com/i/web/status/1474481634770567170","url":"https://t.co/rwM2zi1XfJ"}],"user_mentions":[{"indices":[0,9],"id":1291945442,"id_str":"1291945442","name":"Pranay Pathole","screen_name":"PPathole"},{"indices":[10,16],"id":13298072,"id_str":"13298072","name":"Tesla","screen_name":"Tesla"}]}},{"ID":1474480124653408259,"Text":"@cyantist It was a shamefully low blow from WSJ","CreatedAt":"Fri Dec 24 20:40:30 +0000 2021","Entities":{"hashtags":[],"media":null,"urls":[],"user_mentions":[{"indices":[0,9],"id":13418552,"id_str":"13418552","name":"Recall 欺善暴丁","screen_name":"cyantist"}]}},{"ID":1474474339596742659,"Text":"@WholeMarsBlog And many other things","CreatedAt":"Fri Dec 24 20:17:31 +0000 2021","Entities":{"hashtags":[],"media":null,"urls":[],"user_mentions":[{"indices":[0,14],"id":1263491240336769026,"id_str":"1263491240336769026","name":"Whole Mars","screen_name":"WholeMarsBlog"}]}},{"ID":1474453269833748480,"Text":"@davidjkon @Tesmanian_com No, that’s some tool with senior editor privileges who keeps putting that there","CreatedAt":"Fri Dec 24 18:53:48 +0000 2021","Entities":{"hashtags":[],"media":null,"urls":[],"user_mentions":[{"indices":[0,10],"id":7090302,"id_str":"7090302","name":"𝗗𝗮𝘃𝗶𝗱 𝗝. 𝗞𝗼𝗻","screen_name":"davidjkon"},{"indices":[11,25],"id":1100520274200416256,"id_str":"1100520274200416256","name":"Tesmanian.com","screen_name":"Tesmanian_com"}]}},{"ID":1474452647566532623,"Text":"@Tesmanian_com “History is written by the victors” except on Wikipedia, as your enemies are still alive \u0026amp; have lots… https://t.co/2qmEDsVWxu","CreatedAt":"Fri Dec 24 18:51:19 +0000 2021","Entities":{"hashtags":[],"media":null,"urls":[{"indices":[121,144],"display_url":"twitter.com/i/web/status/1…","expanded_url":"https://twitter.com/i/web/status/1474452647566532623","url":"https://t.co/2qmEDsVWxu"}],"user_mentions":[{"indices":[0,14],"id":1100520274200416256,"id_str":"1100520274200416256","name":"Tesmanian.com","screen_name":"Tesmanian_com"}]}},{"ID":1474452323011289094,"Text":"@Tesmanian_com My wiki is such a dumpster fire 🤣🤣. That’s how you know it isn’t curated.","CreatedAt":"Fri Dec 24 18:50:02 +0000 2021","Entities":{"hashtags":[],"media":null,"urls":[],"user_mentions":[{"indices":[0,14],"id":1100520274200416256,"id_str":"1100520274200416256","name":"Tesmanian.com","screen_name":"Tesmanian_com"}]}},{"ID":1474451624013795336,"Text":"@GerberKawasaki A lot will be added","CreatedAt":"Fri Dec 24 18:47:15 +0000 2021","Entities":{"hashtags":[],"media":null,"urls":[],"user_mentions":[{"indices":[0,15],"id":349249475,"id_str":"349249475","name":"Ross Gerber","screen_name":"GerberKawasaki"}]}},{"ID":1474406965938114560,"Text":"Tesla holiday software update goes to wide release today!","CreatedAt":"Fri Dec 24 15:49:48 +0000 2021","Entities":{"hashtags":[],"media":null,"urls":[],"user_mentions":[]}},{"ID":1474405612662530077,"Text":"@WholeMarsBlog Tesla is technically a car like an iPhone is technically a phone","CreatedAt":"Fri Dec 24 15:44:25 +0000 2021","Entities":{"hashtags":[],"media":null,"urls":[],"user_mentions":[{"indices":[0,14],"id":1263491240336769026,"id_str":"1263491240336769026","name":"Whole Mars","screen_name":"WholeMarsBlog"}]}},{"ID":1474144811951214592,"Text":"10.8 looks good, rolling out today","CreatedAt":"Thu Dec 23 22:28:06 +0000 2021","Entities":{"hashtags":[],"media":null,"urls":[],"user_mentions":[]}},{"ID":1474101621508476931,"Text":"@BLKMDL3 Good idea","CreatedAt":"Thu Dec 23 19:36:28 +0000 2021","Entities":{"hashtags":[],"media":null,"urls":[],"user_mentions":[{"indices":[0,8],"id":988975103785365504,"id_str":"988975103785365504","name":"Zack","screen_name":"BLKMDL3"}]}},{"ID":1473914193527070770,"Text":"@BillyM2k @jack @gladstein @rahilla @farokh @samkazemian @TheSmarmyBum @ethereum That’s why I’m pro Doge","CreatedAt":"Thu Dec 23 07:11:42 +0000 2021","Entities":{"hashtags":[],"media":null,"urls":[],"user_mentions":[{"indices":[0,9],"id":30699048,"id_str":"30699048","name":"Shibetoshi Nakamoto","screen_name":"BillyM2k"},{"indices":[10,15],"id":12,"id_str":"12","name":"jack⚡️","screen_name":"jack"},{"indices":[16,26],"id":19721574,"id_str":"19721574","name":"Alex Gladstein 🌋 ⚡","screen_name":"gladstein"},{"indices":[27,35],"id":15393162,"id_str":"15393162","name":"rahilla.eth","screen_name":"rahilla"},{"indices":[36,43],"id":3369243892,"id_str":"3369243892","name":"Farokh.ethᵍᵐ","screen_name":"farokh"},{"indices":[44,56],"id":3265756934,"id_str":"3265756934","name":"Sam Kazemian (¤, ¤)","screen_name":"samkazemian"},{"indices":[57,70],"id":16689451,"id_str":"16689451","name":"Justin Taylor","screen_name":"TheSmarmyBum"},{"indices":[71,80],"id":2312333412,"id_str":"2312333412","name":"Ethereum","screen_name":"ethereum"}]}},{"ID":1473824879820615680,"Text":"The @SkepticsGuide book is 👍","CreatedAt":"Thu Dec 23 01:16:48 +0000 2021","Entities":{"hashtags":[],"media":null,"urls":[],"user_mentions":[{"indices":[4,18],"id":14283618,"id_str":"14283618","name":"The Skeptics' Guide To The Universe","screen_name":"SkepticsGuide"}]}},{"ID":1473814525774336006,"Text":"Lots of Tesla cars to deliver before year end! Your support in taking delivery is much appreciated. \n\nThanks also t… https://t.co/66GNmieWk1","CreatedAt":"Thu Dec 23 00:35:39 +0000 2021","Entities":{"hashtags":[],"media":null,"urls":[{"indices":[117,140],"display_url":"twitter.com/i/web/status/1…","expanded_url":"https://twitter.com/i/web/status/1473814525774336006","url":"https://t.co/66GNmieWk1"}],"user_mentions":[]}},{"ID":1473804628403834886,"Text":"@scottwww @realrobcopeland Yeah, I didn’t have a house in the Bay Area for over a decade, despite spending half the week there","CreatedAt":"Wed Dec 22 23:56:20 +0000 2021","Entities":{"hashtags":[],"media":null,"urls":[],"user_mentions":[{"indices":[0,9],"id":35293052,"id_str":"35293052","name":"Scott Wainner","screen_name":"scottwww"},{"indices":[10,26],"id":97966078,"id_str":"97966078","name":"Rob Copeland","screen_name":"realrobcopeland"}]}},{"ID":1473794952719224836,"Text":"Whereas radar has trouble seeing small pedestrians, they’re obvious to Tesla vision https://t.co/ANUy58lgl7","CreatedAt":"Wed Dec 22 23:17:53 +0000 2021","Entities":{"hashtags":[],"media":null,"urls":[{"indices":[84,107],"display_url":"twitter.com/Tesla/status/1…","expanded_url":"https://twitter.com/Tesla/status/1473703608654913538","url":"https://t.co/ANUy58lgl7"}],"user_mentions":[]}},{"ID":1473793631354040322,"Text":"@nurodev Disney restricted us to US only","CreatedAt":"Wed Dec 22 23:12:38 +0000 2021","Entities":{"hashtags":[],"media":null,"urls":[],"user_mentions":[{"indices":[0,8],"id":2223516397,"id_str":"2223516397","name":"nuro","screen_name":"nurodev"}]}},{"ID":1473780058083020801,"Text":"@JeffTutorials Yes, but if we find unexpected bugs, release might be delayed until 24th","CreatedAt":"Wed Dec 22 22:18:42 +0000 2021","Entities":{"hashtags":[],"media":null,"urls":[],"user_mentions":[{"indices":[0,14],"id":2694154514,"id_str":"2694154514","name":"Jeff 💙✌️","screen_name":"JeffTutorials"}]}},{"ID":1473779281159467014,"Text":"@WillFealey Yes","CreatedAt":"Wed Dec 22 22:15:36 +0000 2021","Entities":{"hashtags":[],"media":null,"urls":[],"user_mentions":[{"indices":[0,11],"id":18762152,"id_str":"18762152","name":"Will Fealey ☀️⚡️🔋🌍🚗","screen_name":"WillFealey"}]}},{"ID":0,"Text":"____________________searching for '@jack' now____________________","CreatedAt":"","Entities":null},{"ID":1476349666832920576,"Text":"Great interview with Mike on the history and future of Bitcoin at Block. He’s the biggest reason we (and I) have ha… https://t.co/WTWyMZbUwB","CreatedAt":"Thu Dec 30 00:29:24 +0000 2021","Entities":{"hashtags":[],"media":null,"urls":[{"indices":[117,140],"display_url":"twitter.com/i/web/status/1…","expanded_url":"https://twitter.com/i/web/status/1476349666832920576","url":"https://t.co/WTWyMZbUwB"}],"user_mentions":[]}},{"ID":1476255308376907778,"Text":"Bitcoin and ⚡️ for activists https://t.co/m3DevlzByx","CreatedAt":"Wed Dec 29 18:14:27 +0000 2021","Entities":{"hashtags":[],"media":null,"urls":[{"indices":[29,52],"display_url":"twitter.com/i/spaces/1rmxP…","expanded_url":"https://twitter.com/i/spaces/1rmxPgVvRZZJN","url":"https://t.co/m3DevlzByx"}],"user_mentions":[]}},{"ID":1476041392359096322,"Text":"https://t.co/qYPB1Y4WV1","CreatedAt":"Wed Dec 29 04:04:26 +0000 2021","Entities":{"hashtags":[],"media":null,"urls":[{"indices":[0,23],"display_url":"beachgrit.com","expanded_url":"https://beachgrit.com/","url":"https://t.co/qYPB1Y4WV1"}],"user_mentions":[]}},{"ID":1474275093912117266,"Text":"@davidbyttow system/real-time","CreatedAt":"Fri Dec 24 07:05:47 +0000 2021","Entities":{"hashtags":[],"media":null,"urls":[],"user_mentions":[{"indices":[0,12],"id":19436496,"id_str":"19436496","name":"David Byttow ₳Ξ","screen_name":"davidbyttow"}]}},{"ID":1474263588651126788,"Text":"rust is a perfect programming language","CreatedAt":"Fri Dec 24 06:20:04 +0000 2021","Entities":{"hashtags":[],"media":null,"urls":[],"user_mentions":[]}},{"ID":1474099774764822530,"Text":"@engvestor @nickcald can one truly see the tweets of one who doesn't tweet?","CreatedAt":"Thu Dec 23 19:29:08 +0000 2021","Entities":{"hashtags":[],"media":null,"urls":[],"user_mentions":[{"indices":[0,10],"id":1164114582845083648,"id_str":"1164114582845083648","name":"vish","screen_name":"engvestor"},{"indices":[11,20],"id":22545732,"id_str":"22545732","name":"Nick Caldwell🔪🧼","screen_name":"nickcald"}]}},{"ID":1474017460370255883,"Text":"@elonmusk @BillyM2k @gladstein @rahilla @farokh @TheSmarmyBum Meaningful break aways from the corporate establishme… https://t.co/hIrTyvW4Zs","CreatedAt":"Thu Dec 23 14:02:03 +0000 2021","Entities":{"hashtags":[],"media":null,"urls":[{"indices":[117,140],"display_url":"twitter.com/i/web/status/1…","expanded_url":"https://twitter.com/i/web/status/1474017460370255883","url":"https://t.co/hIrTyvW4Zs"}],"user_mentions":[{"indices":[0,9],"id":44196397,"id_str":"44196397","name":"Elon Musk","screen_name":"elonmusk"},{"indices":[10,19],"id":30699048,"id_str":"30699048","name":"Shibetoshi Nakamoto","screen_name":"BillyM2k"},{"indices":[20,30],"id":19721574,"id_str":"19721574","name":"Alex Gladstein 🌋 ⚡","screen_name":"gladstein"},{"indices":[31,39],"id":15393162,"id_str":"15393162","name":"rahilla.eth","screen_name":"rahilla"},{"indices":[40,47],"id":3369243892,"id_str":"3369243892","name":"Farokh.ethᵍᵐ","screen_name":"farokh"},{"indices":[48,61],"id":16689451,"id_str":"16689451","name":"Justin Taylor","screen_name":"TheSmarmyBum"}]}},{"ID":1473899219773755397,"Text":"@jeffseibert Meanwhile in simulation #3…","CreatedAt":"Thu Dec 23 06:12:12 +0000 2021","Entities":{"hashtags":[],"media":null,"urls":[],"user_mentions":[{"indices":[0,12],"id":8798682,"id_str":"8798682","name":"Jeff Seibert","screen_name":"jeffseibert"}]}},{"ID":1473890695463243777,"Text":"From a16z website: \n\n“We aim to connect entrepreneurs, investors, executives, engineers, academics, industry expert… https://t.co/BKnY9N6mUp","CreatedAt":"Thu Dec 23 05:38:20 +0000 2021","Entities":{"hashtags":[],"media":null,"urls":[{"indices":[117,140],"display_url":"twitter.com/i/web/status/1…","expanded_url":"https://twitter.com/i/web/status/1473890695463243777","url":"https://t.co/BKnY9N6mUp"}],"user_mentions":[]}},{"ID":1473888460100575239,"Text":"@samkazemian @TheSmarmyBum @rahilla @farokh @ethereum You’re missing all the points. I’m telling you I’ve learned f… https://t.co/ET96nCfp8Q","CreatedAt":"Thu Dec 23 05:29:27 +0000 2021","Entities":{"hashtags":[],"media":null,"urls":[{"indices":[117,140],"display_url":"twitter.com/i/web/status/1…","expanded_url":"https://twitter.com/i/web/status/1473888460100575239","url":"https://t.co/ET96nCfp8Q"}],"user_mentions":[{"indices":[0,12],"id":3265756934,"id_str":"3265756934","name":"Sam Kazemian (¤, ¤)","screen_name":"samkazemian"},{"indices":[13,26],"id":16689451,"id_str":"16689451","name":"Justin Taylor","screen_name":"TheSmarmyBum"},{"indices":[27,35],"id":15393162,"id_str":"15393162","name":"rahilla.eth","screen_name":"rahilla"},{"indices":[36,43],"id":3369243892,"id_str":"3369243892","name":"Farokh.ethᵍᵐ","screen_name":"farokh"},{"indices":[44,53],"id":2312333412,"id_str":"2312333412","name":"Ethereum","screen_name":"ethereum"}]}},{"ID":1473887809211711491,"Text":"@rahilla @farokh @samkazemian @TheSmarmyBum @ethereum I’m not anti ETH. I’m anti-centralized, VC-owned, single poin… https://t.co/NwekZ8VpbU","CreatedAt":"Thu Dec 23 05:26:51 +0000 2021","Entities":{"hashtags":[],"media":null,"urls":[{"indices":[117,140],"display_url":"twitter.com/i/web/status/1…","expanded_url":"https://twitter.com/i/web/status/1473887809211711491","url":"https://t.co/NwekZ8VpbU"}],"user_mentions":[{"indices":[0,8],"id":15393162,"id_str":"15393162","name":"rahilla.eth","screen_name":"rahilla"},{"indices":[9,16],"id":3369243892,"id_str":"3369243892","name":"Farokh.ethᵍᵐ","screen_name":"farokh"},{"indices":[17,29],"id":3265756934,"id_str":"3265756934","name":"Sam Kazemian (¤, ¤)","screen_name":"samkazemian"},{"indices":[30,43],"id":16689451,"id_str":"16689451","name":"Justin Taylor","screen_name":"TheSmarmyBum"},{"indices":[44,53],"id":2312333412,"id_str":"2312333412","name":"Ethereum","screen_name":"ethereum"}]}},{"ID":1473886113190273031,"Text":"@agarwal Life is too short","CreatedAt":"Thu Dec 23 05:20:07 +0000 2021","Entities":{"hashtags":[],"media":null,"urls":[],"user_mentions":[{"indices":[0,8],"id":15105000,"id_str":"15105000","name":"Sachin Agarwal","screen_name":"agarwal"}]}},{"ID":1473883204801245184,"Text":"@samkazemian @TheSmarmyBum @farokh Scroll up","CreatedAt":"Thu Dec 23 05:08:34 +0000 2021","Entities":{"hashtags":[],"media":null,"urls":[],"user_mentions":[{"indices":[0,12],"id":3265756934,"id_str":"3265756934","name":"Sam Kazemian (¤, ¤)","screen_name":"samkazemian"},{"indices":[13,26],"id":16689451,"id_str":"16689451","name":"Justin Taylor","screen_name":"TheSmarmyBum"},{"indices":[27,34],"id":3369243892,"id_str":"3369243892","name":"Farokh.ethᵍᵐ","screen_name":"farokh"}]}},{"ID":1473880697815420929,"Text":"@samkazemian @TheSmarmyBum @farokh I care only about decentralized, secure, private foundations without single poin… https://t.co/PdkgPY15qI","CreatedAt":"Thu Dec 23 04:58:36 +0000 2021","Entities":{"hashtags":[],"media":null,"urls":[{"indices":[117,140],"display_url":"twitter.com/i/web/status/1…","expanded_url":"https://twitter.com/i/web/status/1473880697815420929","url":"https://t.co/PdkgPY15qI"}],"user_mentions":[{"indices":[0,12],"id":3265756934,"id_str":"3265756934","name":"Sam Kazemian (¤, ¤)","screen_name":"samkazemian"},{"indices":[13,26],"id":16689451,"id_str":"16689451","name":"Justin Taylor","screen_name":"TheSmarmyBum"},{"indices":[27,34],"id":3369243892,"id_str":"3369243892","name":"Farokh.ethᵍᵐ","screen_name":"farokh"}]}},{"ID":1473879848091332608,"Text":"@LarrotizPablo @elonmusk Yes I do. And there are both risks and people trying to take advantage which you want to be aware of.","CreatedAt":"Thu Dec 23 04:55:13 +0000 2021","Entities":{"hashtags":[],"media":null,"urls":[],"user_mentions":[{"indices":[0,14],"id":1174701342943670277,"id_str":"1174701342943670277","name":"Pablo Moncada-Larrotiz (🌜,🌛)","screen_name":"LarrotizPablo"},{"indices":[15,24],"id":44196397,"id_str":"44196397","name":"Elon Musk","screen_name":"elonmusk"}]}},{"ID":1473873968746672130,"Text":"@TheSmarmyBum @farokh 💯 be aware of what’s happening around you","CreatedAt":"Thu Dec 23 04:31:52 +0000 2021","Entities":{"hashtags":[],"media":null,"urls":[],"user_mentions":[{"indices":[0,13],"id":16689451,"id_str":"16689451","name":"Justin Taylor","screen_name":"TheSmarmyBum"},{"indices":[14,21],"id":3369243892,"id_str":"3369243892","name":"Farokh.ethᵍᵐ","screen_name":"farokh"}]}},{"ID":1473873597101977600,"Text":"@farokh I promise this is a fight against the “rich dudes” taking advantage of people like you who should own it all","CreatedAt":"Thu Dec 23 04:30:23 +0000 2021","Entities":{"hashtags":[],"media":null,"urls":[],"user_mentions":[{"indices":[0,7],"id":3369243892,"id_str":"3369243892","name":"Farokh.ethᵍᵐ","screen_name":"farokh"}]}},{"ID":1473872396461477892,"Text":"@einarvollset @cdixon Know who owns what, and what incentivizes them. That’s all.","CreatedAt":"Thu Dec 23 04:25:37 +0000 2021","Entities":{"hashtags":[],"media":null,"urls":[],"user_mentions":[{"indices":[0,13],"id":9232562,"id_str":"9232562","name":"Einar Vollset 🇳🇴🇺🇸","screen_name":"einarvollset"},{"indices":[14,21],"id":2529971,"id_str":"2529971","name":"cdixon.eth","screen_name":"cdixon"}]}},{"ID":1473872142685155333,"Text":"@einarvollset @cdixon Worst thing we did. I wasn’t running company at the time. Company has worked hard and will co… https://t.co/KBcM90rYWY","CreatedAt":"Thu Dec 23 04:24:36 +0000 2021","Entities":{"hashtags":[],"media":null,"urls":[{"indices":[117,140],"display_url":"twitter.com/i/web/status/1…","expanded_url":"https://twitter.com/i/web/status/1473872142685155333","url":"https://t.co/KBcM90rYWY"}],"user_mentions":[{"indices":[0,13],"id":9232562,"id_str":"9232562","name":"Einar Vollset 🇳🇴🇺🇸","screen_name":"einarvollset"},{"indices":[14,21],"id":2529971,"id_str":"2529971","name":"cdixon.eth","screen_name":"cdixon"}]}},{"ID":1473864409260834819,"Text":"@austin_rief I just want a hug in the metaverse™️","CreatedAt":"Thu Dec 23 03:53:52 +0000 2021","Entities":{"hashtags":[],"media":null,"urls":[],"user_mentions":[{"indices":[0,12],"id":158610400,"id_str":"158610400","name":"Austin Rief ☕️","screen_name":"austin_rief"}]}},{"ID":1473863284889690113,"Text":"@loganbartlett https://t.co/4hFbIHGERr","CreatedAt":"Thu Dec 23 03:49:24 +0000 2021","Entities":{"hashtags":[],"media":[{"indices":[15,38],"display_url":"pic.twitter.com/4hFbIHGERr","expanded_url":"https://twitter.com/jack/status/1473863284889690113/photo/1","url":"https://t.co/4hFbIHGERr","id":1473863282096316419,"id_str":"1473863282096316419","media_url":"http://pbs.twimg.com/media/FHQ22KDXoAM-pk7.jpg","media_url_https":"https://pbs.twimg.com/media/FHQ22KDXoAM-pk7.jpg","source_status_id":0,"source_status_id_str":"","type":"photo","sizes":{"thumb":{"w":150,"h":150,"resize":"crop"},"large":{"w":516,"h":493,"resize":"fit"},"medium":{"w":516,"h":493,"resize":"fit"},"small":{"w":516,"h":493,"resize":"fit"}},"video_info":{"aspect_ratio":[0,0],"duration_millis":0,"variants":null}}],"urls":[],"user_mentions":[{"indices":[0,14],"id":123060735,"id_str":"123060735","name":"logan bartlett","screen_name":"loganbartlett"}]}},{"ID":1473814269296848899,"Text":"@tyler And I will still appreciate you through Cameron","CreatedAt":"Thu Dec 23 00:34:38 +0000 2021","Entities":{"hashtags":[],"media":null,"urls":[],"user_mentions":[{"indices":[0,6],"id":24222556,"id_str":"24222556","name":"Tyler Winklevoss","screen_name":"tyler"}]}},{"ID":1473812556443787266,"Text":"@Jason It’s time to block","CreatedAt":"Thu Dec 23 00:27:50 +0000 2021","Entities":{"hashtags":[],"media":null,"urls":[],"user_mentions":[{"indices":[0,6],"id":3840,"id_str":"3840","name":"jason@calacanis.com","screen_name":"Jason"}]}},{"ID":1473809023719849989,"Text":"@johnbattelle @a16z when’s a good time for you?","CreatedAt":"Thu Dec 23 00:13:47 +0000 2021","Entities":{"hashtags":[],"media":null,"urls":[],"user_mentions":[{"indices":[0,13],"id":14600116,"id_str":"14600116","name":"John Battelle","screen_name":"johnbattelle"},{"indices":[14,19],"id":64844802,"id_str":"64844802","name":"a16z","screen_name":"a16z"}]}},{"ID":1473802006355582977,"Text":"this mission statement has always felt so…dark https://t.co/82hFvTd7fO","CreatedAt":"Wed Dec 22 23:45:54 +0000 2021","Entities":{"hashtags":[],"media":[{"indices":[47,70],"display_url":"pic.twitter.com/82hFvTd7fO","expanded_url":"https://twitter.com/jack/status/1473802006355582977/photo/1","url":"https://t.co/82hFvTd7fO","id":1473802002320797705,"id_str":"1473802002320797705","media_url":"http://pbs.twimg.com/media/FHP_HNGXMAkETSO.jpg","media_url_https":"https://pbs.twimg.com/media/FHP_HNGXMAkETSO.jpg","source_status_id":0,"source_status_id_str":"","type":"photo","sizes":{"thumb":{"w":150,"h":150,"resize":"crop"},"large":{"w":1170,"h":662,"resize":"fit"},"medium":{"w":1170,"h":662,"resize":"fit"},"small":{"w":680,"h":385,"resize":"fit"}},"video_info":{"aspect_ratio":[0,0],"duration_millis":0,"variants":null}}],"urls":[],"user_mentions":[]}},{"ID":1473799761438326790,"Text":"“we invest in software eating the world”\n\n*web","CreatedAt":"Wed Dec 22 23:36:59 +0000 2021","Entities":{"hashtags":[],"media":null,"urls":[],"user_mentions":[]}},{"ID":1473764319393427476,"Text":"@mdudas @wongmjane Hm. I didn’t unfollow you.","CreatedAt":"Wed Dec 22 21:16:09 +0000 2021","Entities":{"hashtags":[],"media":null,"urls":[],"user_mentions":[{"indices":[0,7],"id":7184612,"id_str":"7184612","name":"Mike DAOdas","screen_name":"mdudas"},{"indices":[8,18],"id":337119125,"id_str":"337119125","name":"Jane Manchun Wong","screen_name":"wongmjane"}]}},{"ID":1473725424387694601,"Text":"I’m officially banned from web3 https://t.co/RrEIAuqE6f","CreatedAt":"Wed Dec 22 18:41:36 +0000 2021","Entities":{"hashtags":[],"media":[{"indices":[32,55],"display_url":"pic.twitter.com/RrEIAuqE6f","expanded_url":"https://twitter.com/jack/status/1473725424387694601/photo/1","url":"https://t.co/RrEIAuqE6f","id":1473725419601936399,"id_str":"1473725419601936399","media_url":"http://pbs.twimg.com/media/FHO5dgPWQA8Grb-.jpg","media_url_https":"https://pbs.twimg.com/media/FHO5dgPWQA8Grb-.jpg","source_status_id":0,"source_status_id_str":"","type":"photo","sizes":{"thumb":{"w":150,"h":150,"resize":"crop"},"large":{"w":1170,"h":886,"resize":"fit"},"medium":{"w":1170,"h":886,"resize":"fit"},"small":{"w":680,"h":515,"resize":"fit"}},"video_info":{"aspect_ratio":[0,0],"duration_millis":0,"variants":null}}],"urls":[],"user_mentions":[]}},{"ID":1473684066792878081,"Text":"@mikec2113 @CashApp 🤘🏼","CreatedAt":"Wed Dec 22 15:57:15 +0000 2021","Entities":{"hashtags":[],"media":null,"urls":[],"user_mentions":[{"indices":[0,10],"id":117550842,"id_str":"117550842","name":"mikec2113","screen_name":"mikec2113"},{"indices":[11,19],"id":1445650784,"id_str":"1445650784","name":"Cash App","screen_name":"CashApp"}]}},{"ID":1473527315116306432,"Text":"@HYPEBEAST “Don’t look right”","CreatedAt":"Wed Dec 22 05:34:23 +0000 2021","Entities":{"hashtags":[],"media":null,"urls":[],"user_mentions":[{"indices":[0,10],"id":18286505,"id_str":"18286505","name":"HYPEBEAST","screen_name":"HYPEBEAST"}]}},{"ID":1473523826357112832,"Text":"@DavidSacks I wouldn’t worry too much…seems it’s only against you.","CreatedAt":"Wed Dec 22 05:20:31 +0000 2021","Entities":{"hashtags":[],"media":null,"urls":[],"user_mentions":[{"indices":[0,11],"id":1137701,"id_str":"1137701","name":"David Sacks","screen_name":"DavidSacks"}]}},{"ID":1473521102643240960,"Text":"@chainyoda @asemota @aeyakovenko @mdudas Exactly","CreatedAt":"Wed Dec 22 05:09:42 +0000 2021","Entities":{"hashtags":[],"media":null,"urls":[],"user_mentions":[{"indices":[0,10],"id":112509659,"id_str":"112509659","name":"Ajit Tripathi","screen_name":"chainyoda"},{"indices":[11,19],"id":5404442,"id_str":"5404442","name":"Osaretin Victor Asemota","screen_name":"asemota"},{"indices":[20,32],"id":2327407569,"id_str":"2327407569","name":"anat◎ly 🦀🤿🏒 🤙","screen_name":"aeyakovenko"},{"indices":[33,40],"id":7184612,"id_str":"7184612","name":"Mike DAOdas (🏌️‍♂️, ⛳️)","screen_name":"mdudas"}]}},{"ID":1473520418359283713,"Text":"@PetesGuide @DavidSacks Terrible you have to tap one more time to get that retweet button!","CreatedAt":"Wed Dec 22 05:06:59 +0000 2021","Entities":{"hashtags":[],"media":null,"urls":[],"user_mentions":[{"indices":[0,11],"id":22064924,"id_str":"22064924","name":"Peter Sheerin","screen_name":"PetesGuide"},{"indices":[12,23],"id":1137701,"id_str":"1137701","name":"David Sacks","screen_name":"DavidSacks"}]}},{"ID":1473515987320328196,"Text":"Only truth left in the world is surf films @theSURFnetwork","CreatedAt":"Wed Dec 22 04:49:22 +0000 2021","Entities":{"hashtags":[],"media":null,"urls":[],"user_mentions":[{"indices":[43,58],"id":47704795,"id_str":"47704795","name":"TheSurfNetwork","screen_name":"theSURFnetwork"}]}},{"ID":1473515879312801793,"Text":"@MartyBent Metaphors distract","CreatedAt":"Wed Dec 22 04:48:56 +0000 2021","Entities":{"hashtags":[],"media":null,"urls":[],"user_mentions":[{"indices":[0,10],"id":375707743,"id_str":"375707743","name":"Marty Bent","screen_name":"MartyBent"}]}},{"ID":1473513190512336900,"Text":"@cz_binance Words.","CreatedAt":"Wed Dec 22 04:38:15 +0000 2021","Entities":{"hashtags":[],"media":null,"urls":[],"user_mentions":[{"indices":[0,11],"id":902926941413453824,"id_str":"902926941413453824","name":"CZ 🔶 Binance","screen_name":"cz_binance"}]}},{"ID":1473506824741601288,"Text":"The VCs are the problem\n\n*not the people","CreatedAt":"Wed Dec 22 04:12:58 +0000 2021","Entities":{"hashtags":[],"media":null,"urls":[],"user_mentions":[]}},{"ID":1473499113211707397,"Text":"@matthewstoller Never","CreatedAt":"Wed Dec 22 03:42:19 +0000 2021","Entities":{"hashtags":[],"media":null,"urls":[],"user_mentions":[{"indices":[0,15],"id":2030711,"id_str":"2030711","name":"Matt Stoller","screen_name":"matthewstoller"}]}},{"ID":1473451450034540550,"Text":"@JeremyRubin Haaaa","CreatedAt":"Wed Dec 22 00:32:55 +0000 2021","Entities":{"hashtags":[],"media":null,"urls":[],"user_mentions":[{"indices":[0,12],"id":379400685,"id_str":"379400685","name":"rubiverse | utxos.org/signals bip-119","screen_name":"JeremyRubin"}]}},{"ID":1473446029840297992,"Text":"https://t.co/m9kb5mtXCS","CreatedAt":"Wed Dec 22 00:11:23 +0000 2021","Entities":{"hashtags":[],"media":null,"urls":[{"indices":[0,23],"display_url":"twitter.com/i/spaces/1zqKV…","expanded_url":"https://twitter.com/i/spaces/1zqKVBovvBAKB","url":"https://t.co/m9kb5mtXCS"}],"user_mentions":[]}},{"ID":1473441836131835912,"Text":"@D_Twitt3r @TheStalwart I follow Mike","CreatedAt":"Tue Dec 21 23:54:43 +0000 2021","Entities":{"hashtags":[],"media":null,"urls":[],"user_mentions":[{"indices":[0,10],"id":4388018962,"id_str":"4388018962","name":"D.","screen_name":"D_Twitt3r"},{"indices":[11,23],"id":14096763,"id_str":"14096763","name":"Joe Weisenthal","screen_name":"TheStalwart"}]}},{"ID":1473441319557251074,"Text":"@beaniemaxi *gn capital","CreatedAt":"Tue Dec 21 23:52:40 +0000 2021","Entities":{"hashtags":[],"media":null,"urls":[],"user_mentions":[{"indices":[0,11],"id":1351139954525696005,"id_str":"1351139954525696005","name":"Beanie","screen_name":"beaniemaxi"}]}},{"ID":1473428081113190400,"Text":"@micsolana I’m concerned to see “the industry” be distracted under false pretenses when we could all be working on… https://t.co/NcR7nFtiXo","CreatedAt":"Tue Dec 21 23:00:04 +0000 2021","Entities":{"hashtags":[],"media":null,"urls":[{"indices":[116,139],"display_url":"twitter.com/i/web/status/1…","expanded_url":"https://twitter.com/i/web/status/1473428081113190400","url":"https://t.co/NcR7nFtiXo"}],"user_mentions":[{"indices":[0,10],"id":18989355,"id_str":"18989355","name":"Mike Solana","screen_name":"micsolana"}]}},{"ID":1473390675538452494,"Text":"@JeremyRubin Correct","CreatedAt":"Tue Dec 21 20:31:25 +0000 2021","Entities":{"hashtags":[],"media":null,"urls":[],"user_mentions":[{"indices":[0,12],"id":379400685,"id_str":"379400685","name":"rubiverse | utxos.org/signals bip-119","screen_name":"JeremyRubin"}]}},{"ID":1473389430002049039,"Text":"@DavidSacks @mysteriouskat Not clear you have a real point","CreatedAt":"Tue Dec 21 20:26:29 +0000 2021","Entities":{"hashtags":[],"media":null,"urls":[],"user_mentions":[{"indices":[0,11],"id":1137701,"id_str":"1137701","name":"David Sacks","screen_name":"DavidSacks"},{"indices":[12,26],"id":15670857,"id_str":"15670857","name":"Katherine Brodsky 🏴‍☠️","screen_name":"mysteriouskat"}]}},{"ID":1473380683896737813,"Text":"💯 https://t.co/YaEO5tLlWl","CreatedAt":"Tue Dec 21 19:51:43 +0000 2021","Entities":{"hashtags":[],"media":null,"urls":[{"indices":[2,25],"display_url":"twitter.com/levelsio/statu…","expanded_url":"https://twitter.com/levelsio/status/1473210405463986177","url":"https://t.co/YaEO5tLlWl"}],"user_mentions":[]}},{"ID":1473373623947771910,"Text":"@DavidSacks @mysteriouskat Your interpretation is wrong","CreatedAt":"Tue Dec 21 19:23:40 +0000 2021","Entities":{"hashtags":[],"media":null,"urls":[],"user_mentions":[{"indices":[0,11],"id":1137701,"id_str":"1137701","name":"David Sacks","screen_name":"DavidSacks"},{"indices":[12,26],"id":15670857,"id_str":"15670857","name":"Katherine Brodsky 🏴‍☠️","screen_name":"mysteriouskat"}]}},{"ID":1473372456232656901,"Text":"@bradmillscan @laurenceaderemi 💯","CreatedAt":"Tue Dec 21 19:19:02 +0000 2021","Entities":{"hashtags":[],"media":null,"urls":[],"user_mentions":[{"indices":[0,13],"id":246911146,"id_str":"246911146","name":"Superbolic Brad 🔑 #FreeRoss","screen_name":"bradmillscan"},{"indices":[14,30],"id":29252850,"id_str":"29252850","name":"laurence","screen_name":"laurenceaderemi"}]}},{"ID":1473364470315507720,"Text":"@gfodor @balajis @bluesky it will ship.","CreatedAt":"Tue Dec 21 18:47:18 +0000 2021","Entities":{"hashtags":[],"media":null,"urls":[],"user_mentions":[{"indices":[0,7],"id":21245713,"id_str":"21245713","name":"gfodor","screen_name":"gfodor"},{"indices":[8,16],"id":2178012643,"id_str":"2178012643","name":"Balaji Srinivasan","screen_name":"balajis"},{"indices":[17,25],"id":1199812749469126657,"id_str":"1199812749469126657","name":"bluesky","screen_name":"bluesky"}]}},{"ID":1473361222825299974,"Text":"@balajis All false. Twitter started as a corporation. It's had corporate incentives from day 1. It's trying to offs… https://t.co/KdxpqbhxtW","CreatedAt":"Tue Dec 21 18:34:23 +0000 2021","Entities":{"hashtags":[],"media":null,"urls":[{"indices":[117,140],"display_url":"twitter.com/i/web/status/1…","expanded_url":"https://twitter.com/i/web/status/1473361222825299974","url":"https://t.co/KdxpqbhxtW"}],"user_mentions":[{"indices":[0,8],"id":2178012643,"id_str":"2178012643","name":"Balaji Srinivasan","screen_name":"balajis"}]}},{"ID":1473322116804079616,"Text":"21/12/21","CreatedAt":"Tue Dec 21 15:59:00 +0000 2021","Entities":{"hashtags":[],"media":null,"urls":[],"user_mentions":[]}}]